tangram_core/App.vue
tangram_core/CommandPalette.vue
tangram_core/HighlightText.vue
tangram_core/__Timeline.vue
tangram_core/__init__.py
tangram_core/__main__.py
tangram_core/_core.cpython-314-x86_64-linux-musl.so
tangram_core/_core.pyi
tangram_core/api.ts
tangram_core/backend.py
tangram_core/components.ts
tangram_core/config.py
tangram_core/dist-frontend/aggregation-layers.js
tangram_core/dist-frontend/aggregation-layers.js.map
tangram_core/dist-frontend/assets/_commonjsHelpers-CqkleIqs.js
tangram_core/dist-frontend/assets/_commonjsHelpers-CqkleIqs.js.map
tangram_core/dist-frontend/assets/array-utils-flat-BBMak426.js
tangram_core/dist-frontend/assets/array-utils-flat-BBMak426.js.map
tangram_core/dist-frontend/assets/assert-cyW4mg7q.js
tangram_core/dist-frontend/assets/assert-cyW4mg7q.js.map
tangram_core/dist-frontend/assets/b612-latin-400-italic-DePNXA0a.woff
tangram_core/dist-frontend/assets/b612-latin-400-italic-a-4GLPtl.woff2
tangram_core/dist-frontend/assets/b612-latin-400-normal-CC98FVm_.woff2
tangram_core/dist-frontend/assets/b612-latin-400-normal-JbZ7xwUX.woff
tangram_core/dist-frontend/assets/b612-latin-700-normal-B_Snq1wd.woff
tangram_core/dist-frontend/assets/b612-latin-700-normal-BinQrnoB.woff2
tangram_core/dist-frontend/assets/clip-extension-D-rbmFPj.js
tangram_core/dist-frontend/assets/clip-extension-D-rbmFPj.js.map
tangram_core/dist-frontend/assets/color-CUNNsFV-.js
tangram_core/dist-frontend/assets/color-CUNNsFV-.js.map
tangram_core/dist-frontend/assets/cube-geometry-v0HQ793i.js
tangram_core/dist-frontend/assets/cube-geometry-v0HQ793i.js.map
tangram_core/dist-frontend/assets/deep-equal-BTW2ZN6S.js
tangram_core/dist-frontend/assets/deep-equal-BTW2ZN6S.js.map
tangram_core/dist-frontend/assets/fly-to-interpolator-CIXGjOdo.js
tangram_core/dist-frontend/assets/fly-to-interpolator-CIXGjOdo.js.map
tangram_core/dist-frontend/assets/geojson-layer-DgMOQ4Qu.js
tangram_core/dist-frontend/assets/geojson-layer-DgMOQ4Qu.js.map
tangram_core-0.3.0.dist-info/METADATA
tangram_core-0.3.0.dist-info/WHEEL
tangram_core-0.3.0.dist-info/entry_points.txt
tangram_core-0.3.0.dist-info/RECORD
