Metadata-Version: 2.4
Name: tangram_core
Version: 0.3.0
Classifier: Development Status :: 4 - Beta
Classifier: Intended Audience :: Science/Research
Classifier: Intended Audience :: Developers
Classifier: License :: OSI Approved :: GNU Affero General Public License v3
Classifier: Programming Language :: Python :: 3
Classifier: Programming Language :: Python :: 3.10
Classifier: Programming Language :: Python :: 3.11
Classifier: Programming Language :: Python :: 3.12
Classifier: Programming Language :: Python :: 3.13
Classifier: Programming Language :: Python :: 3.14
Classifier: Programming Language :: Rust
Classifier: Topic :: Scientific/Engineering :: Visualization
Classifier: Topic :: System :: Monitoring
Classifier: Operating System :: OS Independent
Requires-Dist: fastapi>=0.115.4
Requires-Dist: uvicorn>=0.32.0
Requires-Dist: redis>=5.2.0
Requires-Dist: httpx[http2]>=0.27.2
Requires-Dist: pydantic>=2.6.1
Requires-Dist: typer
Requires-Dist: tomli ; python_full_version < '3.11'
Requires-Dist: platformdirs>=4.5.0
Requires-Dist: orjson>=3
Summary: A framework for real-time air traffic management research
Home-Page: https://mode-s.org/tangram/
Author-email: Xavier Olive <git@xoolive.org>, Junzi Sun <git@junzis.com>, Xiaogang Huang <maple.hl@gmail.com>, Michel Khalaf <khalafmichel98@gmail.com>, Abraham Cheung <abraham@ylcheung.com>
License-Expression: AGPL-3.0
Requires-Python: >=3.10
